odoo/addons/purchase_quick_intercompany/README.rst
odoo/addons/purchase_quick_intercompany/__init__.py
odoo/addons/purchase_quick_intercompany/__manifest__.py
odoo/addons/purchase_quick_intercompany/i18n/fr.po
odoo/addons/purchase_quick_intercompany/i18n/purchase_quick_intercompany.pot
odoo/addons/purchase_quick_intercompany/models/__init__.py
odoo/addons/purchase_quick_intercompany/models/product_product.py
odoo/addons/purchase_quick_intercompany/models/product_template.py
odoo/addons/purchase_quick_intercompany/readme/CONTRIBUTORS.rst
odoo/addons/purchase_quick_intercompany/readme/DESCRIPTION.rst
odoo/addons/purchase_quick_intercompany/readme/USAGE.rst
odoo/addons/purchase_quick_intercompany/static/description/icon.png
odoo/addons/purchase_quick_intercompany/static/description/index.html
odoo/addons/purchase_quick_intercompany/tests/__init__.py
odoo/addons/purchase_quick_intercompany/tests/test_purchase_quick_intercompany.py
odoo/addons/purchase_quick_intercompany/views/product_template_view.xml
odoo/addons/purchase_quick_intercompany/views/product_view.xml
odoo14_addon_purchase_quick_intercompany-14.0.0.1.1.dist-info/METADATA
odoo14_addon_purchase_quick_intercompany-14.0.0.1.1.dist-info/WHEEL
odoo14_addon_purchase_quick_intercompany-14.0.0.1.1.dist-info/top_level.txt
odoo14_addon_purchase_quick_intercompany-14.0.0.1.1.dist-info/RECORD
